secodadk/__init__.py
secodadk/core.py
secodadk/ingestion_models.py
secodadk/strats/__init__.py
secodadk/strats/core.py
secodadk/strats/custom.py
secodadk/strats/default.py
secodadk-0.0.6.dist-info/LICENSE
secodadk-0.0.6.dist-info/METADATA
secodadk-0.0.6.dist-info/WHEEL
secodadk-0.0.6.dist-info/RECORD
