Metadata-Version: 2.1
Name: secodadk
Version: 0.0.6
Summary: Secoda Development Kit for building Secoda integrations
Author: Secoda Engineering
Author-email: engineering@secoda.co
Requires-Python: >=3.9,<4.0
Classifier: Programming Language :: Python :: 3
Classifier: Programming Language :: Python :: 3.9
Classifier: Programming Language :: Python :: 3.10
Classifier: Programming Language :: Python :: 3.11
Classifier: Programming Language :: Python :: 3.12
Requires-Dist: boto3 (>=1.28.29,<2.0.0)
Requires-Dist: httpx (>=0.26.0,<0.27.0)
Requires-Dist: mypy-boto3-s3 (>=1.28.55,<2.0.0)
Requires-Dist: pandas (>=2.2.1,<3.0.0)
Requires-Dist: pydantic (>=2.4.2,<3.0.0)
